digipin/__init__.py
digipin/module.py
digipin-2.0.1.dist-info/licenses/LICENSE
digipin-2.0.1.dist-info/METADATA
digipin-2.0.1.dist-info/WHEEL
digipin-2.0.1.dist-info/top_level.txt
digipin-2.0.1.dist-info/RECORD
