Metadata-Version: 2.4
Name: digipin
Version: 2.0.1
Summary: A Python module for encoding and decoding DIGIPIN, an alphanumeric representation of latitude and longitude as per final specification of DIGIPIN.
Home-page: https://github.com/goki75/digipin
Author: G Kiran
Author-email: G Kiran <goki75@gmail.com>
License: MIT
Project-URL: homepage, https://github.com/goki75/digipin
Project-URL: repository, https://github.com/goki75/digipin
Keywords: location,geography,encoding,decoding,latitude,longitude
Classifier: Programming Language :: Python :: 3
Classifier: License :: OSI Approved :: MIT License
Classifier: Intended Audience :: Developers
Classifier: Topic :: Software Development :: Libraries :: Python Modules
Requires-Python: >=3.1
License-File: LICENSE
Dynamic: author
Dynamic: home-page
Dynamic: license-file
Dynamic: requires-python
